{
  "publishers": [], 
  "dimensions": "3 1/4 x 3 1/4", 
  "rights": null, 
  "credit_line": "Gift of Mr. and Mrs. Roman Radecki", 
  "artisinal:provider": "http://www.brooklynintegers.com/", 
  "title": "compact in original box", 
  "accession_number": "75.871", 
  "period": null, 
  "artisinal:id": 18156563, 
  "creation_date": "1920-1940", 
  "dynasty": null, 
  "materials": "Gold Metal | mirror | Cardboard Box | Flannel Case", 
  "actors": [], 
  "irn": 10643, 
  "printers": [], 
  "cultures": [], 
  "on_view": false
}