{
  "publishers": [], 
  "dimensions": "10 1/2 x 11 1/2 in.", 
  "rights": null, 
  "credit_line": "The Eliza M. and Sarah L. Niblack Collection", 
  "artisinal:provider": "http://www.brooklynintegers.com/", 
  "title": "fragment; Qalamkar", 
  "accession_number": "33.991", 
  "period": null, 
  "artisinal:id": 18156943, 
  "creation_date": "early 20C.", 
  "dynasty": null, 
  "materials": "metallic threads", 
  "actors": [], 
  "irn": 10789, 
  "printers": [], 
  "cultures": [], 
  "on_view": false
}