{
  "publishers": [], 
  "dimensions": null, 
  "rights": null, 
  "credit_line": "Bequest of Ruth Allison Lilly", 
  "artisinal:provider": "http://www.brooklynintegers.com/", 
  "title": "watch (in the form of a drum) with vinaigrette case  (case: Austria) (watch:  Switzerland)", 
  "accession_number": "73.70.22", 
  "period": null, 
  "artisinal:id": 18169129, 
  "creation_date": "1775-1800", 
  "dynasty": null, 
  "materials": "gold, engraved, enameled, Basse Taille, champleve enamel", 
  "actors": [], 
  "irn": 15906, 
  "printers": [], 
  "cultures": [], 
  "on_view": true
}