{
  "publishers": [], 
  "dimensions": "L: 51 1/4 in. (gown)", 
  "rights": null, 
  "credit_line": "Gift of Ambassador George Feldman and Miss Margot Feldman from the Collection and in memory of Mario", 
  "artisinal:provider": "http://www.brooklynintegers.com/", 
  "title": "EVENING DRESS WITH WRAP", 
  "accession_number": "1984.80", 
  "period": null, 
  "artisinal:id": 18168849, 
  "creation_date": "1970", 
  "dynasty": null, 
  "materials": "silk organza | printed | Silk Crepe De Chine", 
  "actors": [], 
  "irn": 15792, 
  "printers": [], 
  "cultures": [], 
  "on_view": false
}