{
  "publishers": [], 
  "artisinal:provider": "http://www.brooklynintegers.com/", 
  "dimensions": "H: 41 in.", 
  "credit_line": "Gift of Mr. and Mrs. Harrison Eiteljorg", 
  "title": "chair for ruler", 
  "rights": null, 
  "accession_number": "1989.1221", 
  "period": null, 
  "artisinal:id": 18198807, 
  "creation_date": "1880-1920", 
  "materials": "wood, pigment, leather", 
  "actors": [], 
  "irn": 22620, 
  "printers": [], 
  "cultures": [
    "Chokwe people"
  ], 
  "dynasty": null, 
  "on_view": false
}