{
  "publishers": [], 
  "artisinal:provider": "http://www.brooklynintegers.com/", 
  "dimensions": null, 
  "credit_line": "Museum Purchase", 
  "title": "Park Landscape with Lake", 
  "rights": null, 
  "accession_number": "74.290", 
  "period": null, 
  "artisinal:id": 18191949, 
  "creation_date": "19th century", 
  "materials": "pencil heightened with white chalk on grey-green sugar paper", 
  "actors": [], 
  "irn": 19577, 
  "printers": [], 
  "cultures": [], 
  "dynasty": null, 
  "on_view": false
}