{
  "publishers": [], 
  "dimensions": "18 7/8 x 24 3/8 in. (image)\n24 5/8 x 34 in. (sheet)", 
  "rights": null, 
  "credit_line": "Gift of Mrs. Chapin C. Foster", 
  "artisinal:provider": "http://www.brooklynintegers.com/", 
  "title": "Elymas the Sorcerer Struck with Blindness", 
  "accession_number": "14.61", 
  "period": null, 
  "artisinal:id": 18158337, 
  "creation_date": "1820", 
  "dynasty": null, 
  "materials": "engraving", 
  "actors": [], 
  "irn": 11371, 
  "printers": [], 
  "cultures": [], 
  "on_view": false
}