{
  "publishers": [], 
  "dimensions": "19 3/8 x 14 1/4 (image)", 
  "rights": null, 
  "credit_line": "A Gift from Mrs. Phyllisann Hibben Courtis to the memory of Louise Douglas Hibben", 
  "artisinal:provider": "http://www.brooklynintegers.com/", 
  "title": "Snow Storm", 
  "accession_number": "S1086.78.2", 
  "period": null, 
  "artisinal:id": 18158353, 
  "creation_date": null, 
  "dynasty": null, 
  "materials": "watercolor on off-white paper", 
  "actors": [], 
  "irn": 11383, 
  "printers": [], 
  "cultures": [], 
  "on_view": false
}