{
  "publishers": [], 
  "dimensions": "36 1/2 x 8 3/4 x 10 in.", 
  "rights": null, 
  "credit_line": "Gift of Mr. and Mrs. Harrison Eiteljorg", 
  "artisinal:provider": "http://www.brooklynintegers.com/", 
  "title": "mother and child figure", 
  "accession_number": "1989.343", 
  "period": null, 
  "artisinal:id": 18158779, 
  "creation_date": "20th century", 
  "dynasty": null, 
  "materials": "wood, pigment, iron", 
  "actors": [], 
  "irn": 11566, 
  "printers": [], 
  "cultures": [
    "Baga people"
  ], 
  "on_view": true
}