{
  "publishers": [], 
  "rights": null, 
  "dimensions": "H: 7 3/4 in.", 
  "credit_line": "Gift of Mr. and Mrs. Harrison Eiteljorg", 
  "artisinal:provider": "http://www.brooklynintegers.com/", 
  "title": "Ifa bowl with four-human figure", 
  "accession_number": "1989.788", 
  "period": null, 
  "artisinal:id": 18135231, 
  "creation_date": null, 
  "materials": null, 
  "actors": [], 
  "irn": 1658, 
  "printers": [], 
  "cultures": [
    "Yoruba people"
  ], 
  "dynasty": null, 
  "on_view": false
}