{
  "publishers": [], 
  "rights": null, 
  "dimensions": null, 
  "credit_line": "Gift of Kate Klein", 
  "artisinal:provider": "http://www.brooklynintegers.com/", 
  "title": "Die H\u00f6hle (The Cavern), plate 37 from 'Zelt'", 
  "accession_number": "72.48.29", 
  "period": null, 
  "artisinal:id": 18134497, 
  "creation_date": "1915", 
  "materials": "etching, aquatint and drypoint", 
  "actors": [], 
  "irn": 1349, 
  "printers": [], 
  "cultures": [], 
  "dynasty": null, 
  "on_view": false
}