{
  "publishers": [], 
  "rights": null, 
  "dimensions": "Diam: 4 1/2 in.", 
  "credit_line": "Gift of Hebbe Richardson and Elizabeth Bispham Knapp in memory of their parents Sophie Heberton Weiss and Charles Robert Weiss", 
  "artisinal:provider": "http://www.brooklynintegers.com/", 
  "title": "toddy plate", 
  "accession_number": "82.276", 
  "period": null, 
  "artisinal:id": 18144101, 
  "creation_date": "about 1826-1850", 
  "materials": null, 
  "actors": [], 
  "irn": 5418, 
  "printers": [], 
  "cultures": [], 
  "dynasty": null, 
  "on_view": false
}