{
  "publishers": [], 
  "rights": null, 
  "dimensions": "25 5/8 x 18 1/2 in. (w/o tassels)", 
  "credit_line": "Museum Accession", 
  "artisinal:provider": "http://www.brooklynintegers.com/", 
  "title": "runner; 'Kells Art Embroideries'", 
  "accession_number": "88.1", 
  "period": null, 
  "artisinal:id": 18144369, 
  "creation_date": "19th century", 
  "materials": "metallic threads", 
  "actors": [], 
  "irn": 5539, 
  "printers": [], 
  "cultures": [], 
  "dynasty": null, 
  "on_view": false
}