{
  "publishers": [], 
  "rights": null, 
  "dimensions": "38 3/4 x 43 in.", 
  "credit_line": "Gift of Mr. Harold T. Christensen", 
  "artisinal:provider": "http://www.brooklynintegers.com/", 
  "title": "woven mat", 
  "accession_number": "S1507.76.22", 
  "period": null, 
  "artisinal:id": 18144439, 
  "creation_date": "mid 1900s", 
  "materials": "plant fiber, kiwi feathers, feathers, yarn", 
  "actors": [], 
  "irn": 5567, 
  "printers": [], 
  "cultures": [
    "Maori people"
  ], 
  "dynasty": null, 
  "on_view": false
}