{
  "publishers": [], 
  "artisinal:provider": "http://www.brooklynintegers.com/", 
  "dimensions": "H: 6 1/8 in. (each)", 
  "credit_line": "Gift of Mrs. Herbert R. Duckwell in memory of her husband", 
  "title": "Vulcan and Bacchante", 
  "rights": null, 
  "accession_number": "52.43A-B", 
  "period": null, 
  "artisinal:id": 18232535, 
  "creation_date": "about 1750", 
  "materials": null, 
  "actors": [], 
  "irn": 37120, 
  "printers": [], 
  "cultures": [], 
  "dynasty": null, 
  "on_view": true
}