{
  "publishers": [], 
  "artisinal:provider": "http://www.brooklynintegers.com/", 
  "dimensions": "34 1/2 x 46 3/4 in.", 
  "credit_line": "Gift of Mrs. John H. Roberts, Jr.", 
  "title": "devotional hanging depicting a Buddhist diety (thangka)", 
  "rights": null, 
  "accession_number": "70.17", 
  "period": null, 
  "artisinal:id": 18208555, 
  "creation_date": "1800s", 
  "materials": "ink and color on cotton", 
  "actors": [], 
  "irn": 26802, 
  "printers": [], 
  "cultures": [], 
  "dynasty": null, 
  "on_view": false
}