{
  "publishers": [], 
  "artisinal:provider": "http://www.brooklynintegers.com/", 
  "dimensions": "67 1/2 x 122 1/2 in.", 
  "credit_line": "Delavan Smith Fund", 
  "title": "furnishing fabric (meniye ye ye)", 
  "rights": null, 
  "accession_number": "1988.27", 
  "period": null, 
  "artisinal:id": 18208063, 
  "creation_date": "1950s-1970s", 
  "materials": "cotton", 
  "actors": [], 
  "irn": 26595, 
  "printers": [], 
  "cultures": [
    "Zarma", 
    "Hausa"
  ], 
  "dynasty": null, 
  "on_view": false
}