{
  "publishers": [], 
  "artisinal:provider": "http://www.brooklynintegers.com/", 
  "dimensions": "H: 8 1/2 in.", 
  "credit_line": "Gift of Thomas T. Solley and Mrs. J. Malcomb de Sieyes in memory of Jane Ridgely Wolcott", 
  "title": "figurine \"spring\"", 
  "rights": null, 
  "accession_number": "59.2", 
  "period": null, 
  "artisinal:id": 18207461, 
  "creation_date": "about 1865", 
  "materials": "porcelain", 
  "actors": [], 
  "irn": 26343, 
  "printers": [], 
  "cultures": [], 
  "dynasty": null, 
  "on_view": false
}