{
  "publishers": [], 
  "artisinal:provider": "http://www.brooklynintegers.com/", 
  "dimensions": null, 
  "credit_line": "Bequest of Kurt F. Pantzer", 
  "title": "Copy of Procris and Cephalus", 
  "rights": null, 
  "accession_number": "80.747.13", 
  "period": null, 
  "artisinal:id": 18247661, 
  "creation_date": "1832", 
  "materials": "pen, ink and brown ink wash on off-white paper", 
  "actors": [], 
  "irn": 42548, 
  "printers": [], 
  "cultures": [], 
  "dynasty": null, 
  "on_view": false
}