{
  "publishers": [], 
  "artisinal:provider": "http://www.brooklynintegers.com/", 
  "dimensions": "72 x 64 in.", 
  "credit_line": "Gift of Mrs. Robert Ashby", 
  "title": "bed cover (coverlet)", 
  "rights": null, 
  "accession_number": "74.557", 
  "period": null, 
  "artisinal:id": 18171369, 
  "creation_date": "first half of 19th century", 
  "materials": "White Cotton Balanced Plain Weave | dark bluesupplementary wefts (overshot)", 
  "actors": [], 
  "irn": 16740, 
  "printers": [], 
  "cultures": [], 
  "dynasty": null, 
  "on_view": false
}