{
    "accession_number": "1991.60", 
    "actors": [], 
    "creation_date": "mid 20C.", 
    "credit_line": "Gift of Clarke C. Campbell in memory of Mrs. Naomi F. Campbell", 
    "cultures": [], 
    "dimensions": "18 1/2 x 110 in.", 
    "dynasty": null, 
    "images": [], 
    "irn": 32431, 
    "materials": "Abaca (musa Textilis) Fiber", 
    "on_view": false, 
    "period": null, 
    "printers": [], 
    "publishers": [], 
    "rights": null, 
    "title": "yardage for tailored garments"
}
