{
    "accession_number": "2000.87", 
    "actors": [], 
    "creation_date": "317-420", 
    "credit_line": "Russell and Becky Curtis Art Purchase Endowment Fund and Miscellaneous Asian Art Fund", 
    "cultures": [], 
    "dimensions": "9 1/8 x 6 1/4 x 6 1/4 in.", 
    "dynasty": "Eastern Jin dynasty", 
    "irn": 38957, 
    "materials": "stoneware with glaze", 
    "on_view": true, 
    "period": null, 
    "printer": [], 
    "publisher": [], 
    "rights": null, 
    "title": "ewer with twin chicken-head spouts and dragon handle"
}
