{
  "publishers": [], 
  "artisinal:provider": "http://www.brooklynintegers.com/", 
  "dimensions": "12 x 12 in.", 
  "credit_line": "Gift of Schuyler V. R. Cammann", 
  "title": "rank insignia, second degree civil, golden pheasant", 
  "rights": null, 
  "accession_number": "50.18", 
  "period": null, 
  "artisinal:id": 18214845, 
  "creation_date": "about 1880", 
  "materials": "Silver Thread | pencil", 
  "actors": [], 
  "irn": 29480, 
  "printers": [], 
  "cultures": [], 
  "dynasty": "Qing dynasty", 
  "on_view": false
}