{
  "publishers": [], 
  "rights": null, 
  "dimensions": "7 x 8 x 4 1/2 in.", 
  "credit_line": "Gift of Bonnie and David Ross", 
  "artisinal:provider": "http://www.brooklynintegers.com/", 
  "title": "stirrup-spout vessel in feline form", 
  "accession_number": "1991.15", 
  "period": null, 
  "artisinal:id": 18140293, 
  "creation_date": null, 
  "materials": "earthenware, pigment", 
  "actors": [], 
  "irn": 3785, 
  "printers": [], 
  "cultures": [], 
  "dynasty": null, 
  "on_view": false
}