{
    "accession_number": "13.352", 
    "actors": [], 
    "creation_date": "Twelfth Dynasty ( 1938-1756 B.C.)", 
    "credit_line": "Gift of Egypt Research Account through Professor W.M. Flinders Petrie", 
    "cultures": [
        "Egyptian"
    ], 
    "dimensions": null, 
    "dynasty": "Twelfth Dynasty", 
    "irn": 49406, 
    "materials": "Pottery", 
    "on_view": false, 
    "period": "Middle Kingdom", 
    "printer": [], 
    "publisher": [], 
    "rights": null, 
    "title": "string of beads"
}
