{
    "accession_number": "81.85", 
    "actors": [], 
    "creation_date": "about 1826-1850", 
    "credit_line": "Gift of Hebbe Richardson and Elizabeth Bispham Knapp in memory of their parents Sophie Heberton Weiss and Charles Robert Weiss", 
    "cultures": [], 
    "dimensions": "Diam: 7 in.", 
    "dynasty": null, 
    "images": [], 
    "irn": 7688, 
    "materials": null, 
    "on_view": false, 
    "period": null, 
    "printers": [], 
    "publishers": [], 
    "rights": null, 
    "title": "plate (one of fourteen)"
}
