{
    "accession_number": "S8487.95.6", 
    "actors": [], 
    "creation_date": "1767", 
    "credit_line": "Gift of Mary Lou and Bret Waller STUDY COLLECTION", 
    "cultures": [], 
    "dimensions": "12 5/16 x 7 15/16 in. |  31.2 x 20.2 cm. (image) |  16 1/8 x 10 7/8 in. |  40.9 x 27.6 cm. (sheet)", 
    "dynasty": null, 
    "irn": 4369, 
    "materials": "engraving", 
    "on_view": false, 
    "period": null, 
    "printers": [], 
    "publishers": [], 
    "rights": null, 
    "title": "Gravure en Taille douce Plate III, page 148"
}
