{
  "publishers": [], 
  "artisinal:provider": "http://www.brooklynintegers.com/", 
  "dimensions": "w/o cord, H: 11 1/16 in.", 
  "credit_line": "Gift of Mr. and Mrs. Harrison Eiteljorg", 
  "title": "heddle pulley", 
  "rights": null, 
  "accession_number": "1989.444", 
  "period": null, 
  "artisinal:id": 18227437, 
  "creation_date": null, 
  "materials": "wood, metal, fiber", 
  "actors": [], 
  "irn": 34900, 
  "printers": [], 
  "cultures": [
    "Guro"
  ], 
  "dynasty": null, 
  "on_view": false
}