{
  "publishers": [], 
  "artisinal:provider": "http://www.brooklynintegers.com/", 
  "dimensions": null, 
  "credit_line": "Gift of Eloise Grayston Hart", 
  "title": "Running off the Wind from R. Ackermann's \"Yachting Scraps\"", 
  "rights": null, 
  "accession_number": "S3814.80.6", 
  "period": null, 
  "artisinal:id": 18273261, 
  "creation_date": "19th Century/2ND QUARTER", 
  "materials": null, 
  "actors": [], 
  "irn": 55723, 
  "printers": [], 
  "cultures": [], 
  "dynasty": null, 
  "on_view": false
}