{
  "publishers": [], 
  "artisinal:provider": "http://www.brooklynintegers.com/", 
  "dimensions": null, 
  "credit_line": "Gift of James and Joybelle Jean", 
  "title": "Window (from the first floor, ballroom, of the Fred B Smith house, Terre Haute, IN)", 
  "rights": null, 
  "accession_number": "S3269.79.2", 
  "period": null, 
  "artisinal:id": 18273397, 
  "creation_date": "20th Century/1ST QUARTER", 
  "materials": null, 
  "actors": [], 
  "irn": 55981, 
  "printers": [], 
  "cultures": [], 
  "dynasty": null, 
  "on_view": false
}