{
  "publishers": [], 
  "rights": null, 
  "dimensions": "9 1/4 x 14 in.", 
  "credit_line": "Gift of Talitha R. Peat in memory of Wilbur D. Peat", 
  "artisinal:provider": "http://www.brooklynintegers.com/", 
  "title": "Scene of Sericulture", 
  "accession_number": "1986.266", 
  "period": null, 
  "artisinal:id": 18147545, 
  "creation_date": null, 
  "materials": "ink and color on silk", 
  "actors": [], 
  "irn": 6864, 
  "printers": [], 
  "cultures": [], 
  "dynasty": "Qing dynasty", 
  "on_view": false
}