{
  "publishers": [], 
  "rights": null, 
  "dimensions": "L: 33 3/4 in.", 
  "credit_line": "Gift of Carolyne Garrigues Socfield in memory of her grandmother Caroline Burford Danner", 
  "artisinal:provider": "http://www.brooklynintegers.com/", 
  "title": "CANE", 
  "accession_number": "1986.412", 
  "period": null, 
  "artisinal:id": 18147703, 
  "creation_date": null, 
  "materials": "bamboo", 
  "actors": [], 
  "irn": 6927, 
  "printers": [], 
  "cultures": [], 
  "dynasty": null, 
  "on_view": false
}