{
  "publishers": [], 
  "artisinal:provider": "http://www.brooklynintegers.com/", 
  "dimensions": "39 x 17 1/4 in.", 
  "credit_line": "Gift of Eliza M. Niblack", 
  "title": "Cover used in Buddhist temple sanctuary (uchishiki)", 
  "rights": null, 
  "accession_number": "16.875", 
  "period": "Meiji", 
  "artisinal:id": 18219985, 
  "creation_date": "1868-1912", 
  "materials": "silk, gold wrapped thread, cotton (lining)", 
  "actors": [], 
  "irn": 31702, 
  "printers": [], 
  "cultures": [
    "Japanese"
  ], 
  "dynasty": null, 
  "on_view": false
}