{
  "publishers": [], 
  "artisinal:provider": "http://www.brooklynintegers.com/", 
  "dimensions": null, 
  "credit_line": "Gift of Olive F. Whitman and Ray Jennings Morehouse, sister and brother of Lucille e. Morehouse, from the Lucille E. Morehouse Estate", 
  "title": "In the Alps", 
  "rights": null, 
  "accession_number": "65.71", 
  "period": null, 
  "artisinal:id": 18218597, 
  "creation_date": "20th century", 
  "materials": "etching on paper", 
  "actors": [], 
  "irn": 31078, 
  "printers": [], 
  "cultures": [], 
  "dynasty": null, 
  "on_view": false
}