{
  "publishers": [], 
  "artisinal:provider": "http://www.brooklynintegers.com/", 
  "dimensions": null, 
  "credit_line": "Museum Accession", 
  "title": "Save the Products of the Land, Eat More Fish They Feed Themselves", 
  "rights": null, 
  "accession_number": "72.12.34C", 
  "period": null, 
  "artisinal:id": 18257881, 
  "creation_date": "1940-1945", 
  "materials": "paper|ink", 
  "actors": [], 
  "irn": 47017, 
  "printers": [], 
  "cultures": [], 
  "dynasty": null, 
  "on_view": false
}