{
  "publishers": [], 
  "artisinal:provider": "http://www.brooklynintegers.com/", 
  "dimensions": "18 1/16 x 13 7/8 in. |  46.2 x 35.2 cm. (image)", 
  "credit_line": "Gift of the Artist", 
  "title": "Untitled (Maninka fiber mask)", 
  "rights": null, 
  "accession_number": "1993.271", 
  "period": null, 
  "artisinal:id": 18172673, 
  "creation_date": "1993", 
  "materials": "gold sepia-toned silver print", 
  "actors": [], 
  "irn": 17211, 
  "printers": [], 
  "cultures": [], 
  "dynasty": null, 
  "on_view": false
}