{
  "publishers": [], 
  "artisinal:provider": "http://www.brooklynintegers.com/", 
  "dimensions": "H: 1 1/2 in.", 
  "credit_line": "Bequest of Julia Jean Stokes", 
  "title": "pendant: frog motif", 
  "rights": null, 
  "accession_number": "1991.293", 
  "period": null, 
  "artisinal:id": 18174151, 
  "creation_date": "800-1500", 
  "materials": "gold", 
  "actors": [], 
  "irn": 17756, 
  "printers": [], 
  "cultures": [
    "Cocl\u00e9 culture | Veraguas culture"
  ], 
  "dynasty": null, 
  "on_view": true
}