{
  "publishers": [], 
  "artisinal:provider": "http://www.brooklynintegers.com/", 
  "dimensions": null, 
  "credit_line": "Gift of David W. Campbell", 
  "title": "coat for evening ensemble", 
  "rights": null, 
  "accession_number": "1986.67A", 
  "period": null, 
  "artisinal:id": 18274821, 
  "creation_date": "about 1962", 
  "materials": "silk shantung gazar with glass beads and cotton thread", 
  "actors": [], 
  "irn": 57875, 
  "printers": [], 
  "cultures": [], 
  "dynasty": null, 
  "on_view": false
}