{
    "accession_number": "1989.371", 
    "actors": [], 
    "creation_date": null, 
    "credit_line": "Gift of Mr. and Mrs. Harrison Eiteljorg", 
    "cultures": [], 
    "dimensions": "approx.L:of bkt.22' | approx.H:hanging 44'", 
    "dynasty": null, 
    "images": [], 
    "irn": 6196, 
    "materials": "Basketry | fiber | cloth", 
    "on_view": false, 
    "period": null, 
    "printers": [], 
    "publishers": [], 
    "rights": null, 
    "title": "bustle with rattle-like elements with Koranic insrciptions"
}
