{
    "accession_number": "S1086.78.8", 
    "actors": [], 
    "creation_date": "1942", 
    "credit_line": "A Gift from Mrs. Phyllisann Hibben Courtis to the memory of Louise Douglas Hibben", 
    "cultures": [], 
    "dimensions": "13 1/2 x 9 3/8", 
    "dynasty": null, 
    "images": [], 
    "irn": 9168, 
    "materials": "watercolor on off-white paper", 
    "on_view": false, 
    "period": null, 
    "printers": [], 
    "publishers": [], 
    "rights": null, 
    "title": "Snow Patches"
}
