{
  "publishers": [], 
  "dimensions": "H: 13 1/2 x W: 10 1/4 in.", 
  "rights": null, 
  "credit_line": "Bequest of Kathryne S. Block", 
  "artisinal:provider": "http://www.brooklynintegers.com/", 
  "title": "PLATTER WITH TULIP AND BUDS AND MOTTLED RED AND BLACK BORDER", 
  "accession_number": "S5704.86.28", 
  "period": null, 
  "artisinal:id": 18166269, 
  "creation_date": "about 1856", 
  "dynasty": null, 
  "materials": null, 
  "actors": [], 
  "irn": 14658, 
  "printers": [], 
  "cultures": [], 
  "on_view": false
}