{
  "publishers": [], 
  "dimensions": "4 3/4 x 5 in.", 
  "rights": null, 
  "credit_line": "The Allen Whitehill Clowes Collection of Bronzes", 
  "artisinal:provider": "http://www.brooklynintegers.com/", 
  "title": "Ewe and Lamb", 
  "accession_number": "78.56", 
  "period": null, 
  "artisinal:id": 18165507, 
  "creation_date": null, 
  "dynasty": null, 
  "materials": "Hollow Cast Bronze | Marble Base", 
  "actors": [], 
  "irn": 14328, 
  "printers": [], 
  "cultures": [], 
  "on_view": false
}