{
  "publishers": [], 
  "artisinal:provider": "http://www.brooklynintegers.com/", 
  "dimensions": "headpiece:H:9 5/8 in./costume:H: 64 in.", 
  "credit_line": "Gift of Mr. and Mrs. Harrison Eiteljorg", 
  "title": "headpiece for masker's costume", 
  "rights": null, 
  "accession_number": "1989.309A", 
  "period": null, 
  "artisinal:id": 18202273, 
  "creation_date": "1900-1999", 
  "materials": "Vegetable Mastic | Seeds | fiber | pigment | Fiber Netting", 
  "actors": [], 
  "irn": 24087, 
  "printers": [], 
  "cultures": [
    "Koro people"
  ], 
  "dynasty": null, 
  "on_view": false
}