{
  "publishers": [], 
  "artisinal:provider": "http://www.brooklynintegers.com/", 
  "dimensions": "65 3/4 x 24 1/4 in. (each panel)", 
  "credit_line": "Mr. and Mrs. William R. Spurlock Fund", 
  "title": "Seven Gods of Good Fortune", 
  "rights": null, 
  "accession_number": "2000.12", 
  "period": "Edo", 
  "artisinal:id": 18235979, 
  "creation_date": "about 1700", 
  "materials": "ink, color and gold leaf on paper, six-fold screen", 
  "actors": [], 
  "irn": 38377, 
  "printers": [], 
  "cultures": [], 
  "dynasty": null, 
  "on_view": false
}