{
  "publishers": [], 
  "artisinal:provider": "http://www.brooklynintegers.com/", 
  "dimensions": "L: 1 7/8 in.", 
  "credit_line": "Gift of Mr. and Mrs. Harrison Eiteljorg", 
  "title": "weight for measuring gold in the form of a cannon", 
  "rights": null, 
  "accession_number": "1989.541", 
  "period": null, 
  "artisinal:id": 18221455, 
  "creation_date": "1800-1950", 
  "materials": "brass", 
  "actors": [], 
  "irn": 32350, 
  "printers": [], 
  "cultures": [
    "Akan people"
  ], 
  "dynasty": null, 
  "on_view": true
}