{
    "accession_number": "1985.441", 
    "actors": [], 
    "creation_date": "about 1900", 
    "credit_line": "Gift of Carolyn Garrigues Scofield in memory of her grandmother Caroline Burford Danner", 
    "cultures": [], 
    "dimensions": "L: 43 5/8 in.", 
    "dynasty": null, 
    "irn": 288, 
    "materials": "Cotton Pieced | embroidered | trimmed | lace", 
    "on_view": false, 
    "period": null, 
    "printers": [], 
    "publishers": [], 
    "rights": null, 
    "title": "WOMAN'S UNDER GARMENT"
}
