{
  "publishers": [], 
  "artisinal:provider": "http://www.brooklynintegers.com/", 
  "dimensions": "33 3/4 x 21 1/2 x 20 1/2 in.", 
  "credit_line": "Gift of the Children of J.K. Lilly Jr.", 
  "title": "open arm side chair", 
  "rights": null, 
  "accession_number": "67.10.41", 
  "period": null, 
  "artisinal:id": 18212419, 
  "creation_date": null, 
  "materials": "wood, caning, fabric", 
  "actors": [], 
  "irn": 28442, 
  "printers": [], 
  "cultures": [], 
  "dynasty": null, 
  "on_view": true
}