{
  "publishers": [], 
  "dimensions": "H: 2 in. |  W: 1 5/8 in. |  D: 1 in.", 
  "rights": null, 
  "credit_line": "Gift of Gene Slaymaker", 
  "artisinal:provider": "http://www.brooklynintegers.com/", 
  "title": "stamp in the form of a monkey", 
  "accession_number": "S6254.86.1", 
  "period": null, 
  "artisinal:id": 18152507, 
  "creation_date": null, 
  "dynasty": null, 
  "materials": "Fired Clay", 
  "actors": [], 
  "irn": 8933, 
  "printers": [], 
  "cultures": [], 
  "on_view": false
}