{
  "publishers": [], 
  "rights": null, 
  "dimensions": "L: 1 1/8 in. W: 3/4 in.", 
  "credit_line": "Gift of Mrs. Hiram Wasson McKee in memory of Grace Wasson Bates", 
  "artisinal:provider": "http://www.brooklynintegers.com/", 
  "title": "VINAIGRETTE", 
  "accession_number": "78.257", 
  "period": null, 
  "artisinal:id": 18151083, 
  "creation_date": "1835-1836", 
  "materials": "Silver-gilt", 
  "actors": [], 
  "irn": 8372, 
  "printers": [], 
  "cultures": [], 
  "dynasty": null, 
  "on_view": false
}