{
  "publishers": [], 
  "artisinal:provider": "http://www.brooklynintegers.com/", 
  "dimensions": "13 1/2 x 13 x 22 1/2 in.", 
  "credit_line": "Gift of Mr. and Mrs. Harrison Eiteljorg", 
  "title": "crocodile helmet mask", 
  "rights": null, 
  "accession_number": "1989.212", 
  "period": null, 
  "artisinal:id": 18196093, 
  "creation_date": "20th century", 
  "materials": "wood, pigment, fiber, gourd, feathers, incrustation", 
  "actors": [], 
  "irn": 21425, 
  "printers": [], 
  "cultures": [
    "Nuna people"
  ], 
  "dynasty": null, 
  "on_view": true
}