{
  "publishers": [], 
  "artisinal:provider": "http://www.brooklynintegers.com/", 
  "dimensions": null, 
  "credit_line": "Carl H. Lieber Memorial Fund and Martha Delzell Memorial Fund", 
  "title": "altar frontal", 
  "rights": null, 
  "accession_number": "1993.79", 
  "period": null, 
  "artisinal:id": 18195607, 
  "creation_date": "1750-1799", 
  "materials": "silk, gold threads", 
  "actors": [], 
  "irn": 21198, 
  "printers": [], 
  "cultures": [], 
  "dynasty": null, 
  "on_view": false
}