{
  "publishers": [], 
  "artisinal:provider": "http://www.brooklynintegers.com/", 
  "dimensions": null, 
  "credit_line": "Gift of Mrs. J.K. Lilly", 
  "title": "Orchid: Cypripedium aurcum confetti", 
  "rights": null, 
  "accession_number": "63.128", 
  "period": null, 
  "artisinal:id": 18255417, 
  "creation_date": "1908", 
  "materials": "watercolor on Whatman's water colour sketching board", 
  "actors": [], 
  "irn": 45888, 
  "printers": [], 
  "cultures": [], 
  "dynasty": null, 
  "on_view": false
}