{
  "publishers": [], 
  "artisinal:provider": "http://www.brooklynintegers.com/", 
  "dimensions": "92 x 44 in.", 
  "credit_line": "The Eliza M. and Sarah L. Niblack Collection", 
  "title": "man's ceremonial wrapper; hinggi", 
  "rights": null, 
  "accession_number": "33.628", 
  "period": null, 
  "artisinal:id": 18231987, 
  "creation_date": "1st quarter of 20C.", 
  "materials": null, 
  "actors": [], 
  "irn": 36876, 
  "printers": [], 
  "cultures": [], 
  "dynasty": null, 
  "on_view": false
}