{
  "publishers": [], 
  "artisinal:provider": "http://www.brooklynintegers.com/", 
  "dimensions": "H: 21 3/8 in. |  54.3 cm. |  W: 23 3/4 in. |  60.3 cm.", 
  "credit_line": "Anonymous Gift", 
  "title": "stool with two figures", 
  "rights": null, 
  "accession_number": "1992.285", 
  "period": null, 
  "artisinal:id": 18230055, 
  "creation_date": null, 
  "materials": "wood", 
  "actors": [], 
  "irn": 36056, 
  "printers": [], 
  "cultures": [
    "Fante people"
  ], 
  "dynasty": null, 
  "on_view": false
}