{
  "publishers": [], 
  "artisinal:provider": "http://www.brooklynintegers.com/", 
  "dimensions": "46 x 94 in. |  116.8 x 238.8 cm.", 
  "credit_line": "Colonel Jeff W. Boucher Collection", 
  "title": "rug", 
  "rights": null, 
  "accession_number": "1996.69", 
  "period": null, 
  "artisinal:id": 18232243, 
  "creation_date": "about 1920", 
  "materials": "wool", 
  "actors": [], 
  "irn": 36993, 
  "printers": [], 
  "cultures": [
    "Baluchi people"
  ], 
  "dynasty": null, 
  "on_view": false
}