{
  "publishers": [], 
  "dimensions": "L: 10 1/4 in.", 
  "rights": null, 
  "credit_line": "Gift of the Children of J. K. Lilly", 
  "artisinal:provider": "http://www.brooklynintegers.com/", 
  "title": "covered dish (in the shape of a duck)", 
  "accession_number": "67.10.265A-B", 
  "period": null, 
  "artisinal:id": 18159921, 
  "creation_date": "p. 1887", 
  "dynasty": null, 
  "materials": "Milk Glass | pressed", 
  "actors": [], 
  "irn": 12095, 
  "printers": [], 
  "cultures": [], 
  "on_view": false
}