{
  "publishers": [], 
  "dimensions": null, 
  "rights": null, 
  "credit_line": "Gift of Olive F. Whitman & Ray Jennings Morehouse, sister and brother of Lucille E. Morehouse, from the Lucille E. Morehouse Estate", 
  "artisinal:provider": "http://www.brooklynintegers.com/", 
  "title": "Bayfield", 
  "accession_number": "65.89", 
  "period": null, 
  "artisinal:id": 18160285, 
  "creation_date": "1939", 
  "dynasty": null, 
  "materials": "etching and aquatint", 
  "actors": [], 
  "irn": 12251, 
  "printers": [], 
  "cultures": [], 
  "on_view": false
}