{
  "publishers": [], 
  "artisinal:provider": "http://www.brooklynintegers.com/", 
  "dimensions": "H: 31", 
  "credit_line": "Gift of the Children of J.K. Lilly", 
  "title": "writing desk (bureau plat)", 
  "rights": null, 
  "accession_number": "67.10.82", 
  "period": null, 
  "artisinal:id": 18206539, 
  "creation_date": "about 1850", 
  "materials": "Gilt Bronze (ormolu) | leather | pen | ink", 
  "actors": [], 
  "irn": 25944, 
  "printers": [], 
  "cultures": [], 
  "dynasty": null, 
  "on_view": true
}