{
  "publishers": [], 
  "artisinal:provider": "http://www.brooklynintegers.com/", 
  "dimensions": "16 3/4 x 9 x 10 in.", 
  "credit_line": "Gift of Mr. and Mrs. Harrison Eiteljorg", 
  "title": "male figure (Nkisi)", 
  "rights": null, 
  "accession_number": "1989.1196", 
  "period": null, 
  "artisinal:id": 18205535, 
  "creation_date": "late 19th century", 
  "materials": "wood, metal, hide, fur, horn, gourd, incrustation", 
  "actors": [], 
  "irn": 25515, 
  "printers": [], 
  "cultures": [
    "Songye people"
  ], 
  "dynasty": null, 
  "on_view": true
}