{
  "publishers": [], 
  "artisinal:provider": "http://www.brooklynintegers.com/", 
  "dimensions": "35 x 94 1/2 in.", 
  "credit_line": "The Eliza M. and Sarah L. Niblack Collection", 
  "title": "woman's head cloth; tengkuluak", 
  "rights": null, 
  "accession_number": "76.336", 
  "period": null, 
  "artisinal:id": 18205361, 
  "creation_date": "1850-1900", 
  "materials": "Cotton Warp | metallic threads", 
  "actors": [], 
  "irn": 25444, 
  "printers": [], 
  "cultures": [], 
  "dynasty": null, 
  "on_view": false
}