{
  "publishers": [], 
  "artisinal:provider": "http://www.brooklynintegers.com/", 
  "dimensions": "2 1/4 x 2 in.", 
  "credit_line": "The Eliza M. and Sarah L. Niblack Collection", 
  "title": "small purse (opened)", 
  "rights": null, 
  "accession_number": "33.1183", 
  "period": null, 
  "artisinal:id": 18206171, 
  "creation_date": "early 1900s", 
  "materials": "silk", 
  "actors": [], 
  "irn": 25785, 
  "printers": [], 
  "cultures": [
    "Balkan", 
    "Persian"
  ], 
  "dynasty": null, 
  "on_view": false
}