{
  "publishers": [], 
  "rights": null, 
  "dimensions": "23 x 24 in. (sight) | 29.75  x 30 x 1 in. (mounted)", 
  "credit_line": "Textile Arts Fund", 
  "artisinal:provider": "http://www.brooklynintegers.com/", 
  "title": "panel with long life and happiness characters", 
  "accession_number": "1998.106", 
  "period": null, 
  "artisinal:id": 18131747, 
  "creation_date": "1401-1450", 
  "materials": "silk damask", 
  "actors": [], 
  "irn": 247, 
  "printers": [], 
  "cultures": [], 
  "dynasty": "Ming dynasty", 
  "on_view": false
}