{
  "publishers": [], 
  "rights": null, 
  "dimensions": null, 
  "credit_line": "Mr. and Mrs. Julius F. Pratt Fund", 
  "artisinal:provider": "http://www.brooklynintegers.com/", 
  "title": "Spring Day, Columbia Missouri", 
  "accession_number": "79.438", 
  "period": null, 
  "artisinal:id": 18133087, 
  "creation_date": "1975", 
  "materials": "pen, ink and ink wash on off-white paper", 
  "actors": [], 
  "irn": 784, 
  "printers": [], 
  "cultures": [], 
  "dynasty": null, 
  "on_view": false
}