{
  "publishers": [], 
  "rights": null, 
  "dimensions": "9 5/8 x 6 x 5 1/2 in.", 
  "credit_line": "Gift of Mr. and Mrs. Harrison Eiteljorg", 
  "artisinal:provider": "http://www.brooklynintegers.com/", 
  "title": "face mask for Kaogle masker", 
  "accession_number": "1989.359", 
  "period": null, 
  "artisinal:id": 18149705, 
  "creation_date": "1890-1930", 
  "materials": "wood, pigment, iron, fiber, cloth, metal", 
  "actors": [], 
  "irn": 7778, 
  "printers": [], 
  "cultures": [
    "Dan people"
  ], 
  "dynasty": null, 
  "on_view": true
}