{
  "publishers": [], 
  "rights": null, 
  "dimensions": "10 15/16 x 13 7/8 in. |  27.8 x 35.2 cm.", 
  "credit_line": "Gift of Stephen H. Ison", 
  "artisinal:provider": "http://www.brooklynintegers.com/", 
  "title": "Stromboli's Orchestra (SEG 4-2)(Pinocchio)", 
  "accession_number": "S8126.93.32", 
  "period": null, 
  "artisinal:id": 18148119, 
  "creation_date": "1939", 
  "materials": "photocopy", 
  "actors": [], 
  "irn": 7092, 
  "printers": [], 
  "cultures": [], 
  "dynasty": null, 
  "on_view": false
}