{
  "publishers": [], 
  "rights": null, 
  "dimensions": "24 \u00be x 13 \u00be x 5 \u00bd in.", 
  "credit_line": "Gift of Mrs. George Phillip Meier", 
  "artisinal:provider": "http://www.brooklynintegers.com/", 
  "title": "cabinet", 
  "accession_number": "41.12", 
  "period": null, 
  "artisinal:id": 18150175, 
  "creation_date": "about 1800", 
  "materials": "wood, cloisonn\u00e9", 
  "actors": [], 
  "irn": 7980, 
  "printers": [], 
  "cultures": [], 
  "dynasty": "Qing dynasty", 
  "on_view": true
}