{
  "publishers": [], 
  "rights": null, 
  "dimensions": "L: 27 in. (tunic)", 
  "credit_line": "Gift of Mrs. Frank C. Springer, Jr.", 
  "artisinal:provider": "http://www.brooklynintegers.com/", 
  "title": "evening dress", 
  "accession_number": "1983.125A-B", 
  "period": null, 
  "artisinal:id": 18137173, 
  "creation_date": "about 1920", 
  "materials": "Silk Satin Embroidered | rhinestones", 
  "actors": [], 
  "irn": 2460, 
  "printers": [], 
  "cultures": [], 
  "dynasty": null, 
  "on_view": false
}