{
  "publishers": [], 
  "rights": null, 
  "dimensions": "H: 6 13/16 inches", 
  "credit_line": "Gift of Mr. and Mrs Harrison Eiteljorg", 
  "artisinal:provider": "http://www.brooklynintegers.com/", 
  "title": "prisoner and guard group", 
  "accession_number": "1989.725", 
  "period": null, 
  "artisinal:id": 18137993, 
  "creation_date": null, 
  "materials": null, 
  "actors": [], 
  "irn": 2809, 
  "printers": [], 
  "cultures": [
    "Yoruba people"
  ], 
  "dynasty": null, 
  "on_view": false
}