{
  "publishers": [], 
  "rights": null, 
  "dimensions": "L: 31 1/2 in.", 
  "credit_line": "Gift of Carolyn Garrigues Scofield in memory of her grandmother Caroline Burford Danner", 
  "artisinal:provider": "http://www.brooklynintegers.com/", 
  "title": "STOCKINGS", 
  "accession_number": "1986.453A-B", 
  "period": null, 
  "artisinal:id": 18137281, 
  "creation_date": "about 1900", 
  "materials": null, 
  "actors": [], 
  "irn": 2507, 
  "printers": [], 
  "cultures": [], 
  "dynasty": null, 
  "on_view": false
}