{
  "publishers": [], 
  "rights": null, 
  "dimensions": "20 x 39 in. |  50.8 x 99.1 cm.", 
  "credit_line": "Colonel Jeff W. Boucher Collection", 
  "artisinal:provider": "http://www.brooklynintegers.com/", 
  "title": "pillow or storage bag", 
  "accession_number": "1996.61", 
  "period": null, 
  "artisinal:id": 18136545, 
  "creation_date": "early 20th century", 
  "materials": "wool", 
  "actors": [], 
  "irn": 2202, 
  "printers": [], 
  "cultures": [
    "Baluchi people"
  ], 
  "dynasty": null, 
  "on_view": false
}