{
  "publishers": [], 
  "rights": null, 
  "dimensions": "L: 6 1/4 in.", 
  "credit_line": "Gift of Miss Katharine M. Klein", 
  "artisinal:provider": "http://www.brooklynintegers.com/", 
  "title": "pie fork (in the Love Disarmed pattern)", 
  "accession_number": "1991.237", 
  "period": null, 
  "artisinal:id": 18138243, 
  "creation_date": "pattern introduced 1905", 
  "materials": null, 
  "actors": [], 
  "irn": 2915, 
  "printers": [], 
  "cultures": [], 
  "dynasty": null, 
  "on_view": false
}