{
  "publishers": [], 
  "artisinal:provider": "http://www.brooklynintegers.com/", 
  "dimensions": "17 ft 4 in. x 40 ft 5 in. (installed)", 
  "credit_line": "Gift of Frederick M. Ayres, William C. Bobbs, Mrs. Linnaeus C. Boyd, Mrs. William H. Coburn, Fred C. Dickson, James I. Dissette, Mrs. Samuel Dowden, Charles W. Fairbanks, Arthur B. Grover, J. Irving Holcomb, Mrs. Jacquelin S. Holliday, Louis C. Huesmann, Mrs. Henry Kahn, Mrs. Ernest Knefler, Hugh McK. Landon, Ralph A. Lemcke, Mrs. Louis H. Levey, Carl H. Lieber, Dr. Carleton B. McCulloch, Edward L. McKee, Volney T. Malott, Walter L. Milliken, Meredith Nicholson, Gustave A. Schnull, Delavan Smith, George G. Snowden, Mrs. Frank D. Stalnaker, Mrs. Clarence Stanley, Miss Lucy M. Taggart, Henry M. Talbott, Booth Tarkington, Ernst M. Wiles, Evans Woollen", 
  "title": "architectural details", 
  "rights": null, 
  "accession_number": "15.70-.204", 
  "period": null, 
  "artisinal:id": 18217965, 
  "creation_date": null, 
  "materials": "carved cedar wood, stone, metal", 
  "actors": [], 
  "irn": 30809, 
  "printers": [], 
  "cultures": [], 
  "dynasty": null, 
  "on_view": false
}