{
  "publishers": [], 
  "artisinal:provider": "http://www.brooklynintegers.com/", 
  "dimensions": "L: 25 1/4 in.", 
  "credit_line": "Gift of Morton and Rebecca Lipkin", 
  "title": "tobacco pipe", 
  "rights": null, 
  "accession_number": "1988.57", 
  "period": null, 
  "artisinal:id": 18190579, 
  "creation_date": null, 
  "materials": "Fiber Cord | Incrustation | Metal Mouth Tube | aquatint", 
  "actors": [], 
  "irn": 18983, 
  "printers": [], 
  "cultures": [], 
  "dynasty": null, 
  "on_view": false
}