{
  "publishers": [], 
  "artisinal:provider": "http://www.brooklynintegers.com/", 
  "dimensions": "12 x 12 1/2 in.", 
  "credit_line": "Gift of Mrs. Sylvia Orrell in memory of Colonel and Mrs. F. J. Keelty", 
  "title": "rank insignia, third degree civil, peacock", 
  "rights": null, 
  "accession_number": "75.796", 
  "period": null, 
  "artisinal:id": 18210695, 
  "creation_date": "about 1880", 
  "materials": "gilt paper | Coral Beads", 
  "actors": [], 
  "irn": 27696, 
  "printers": [], 
  "cultures": [], 
  "dynasty": "Qing dynasty", 
  "on_view": false
}