{
  "publishers": [], 
  "dimensions": "10 1/2 x 9 in.", 
  "rights": null, 
  "credit_line": "The Eliza M. and Sarah L. Niblack Collection", 
  "artisinal:provider": "http://www.brooklynintegers.com/", 
  "title": "Sash fragment \"uckur\" or \"kusak\" | embroidery fragment", 
  "accession_number": "33.1131F", 
  "period": null, 
  "artisinal:id": 18153751, 
  "creation_date": "20th Century", 
  "dynasty": null, 
  "materials": "cotton", 
  "actors": [], 
  "irn": 9441, 
  "printers": [], 
  "cultures": [], 
  "on_view": false
}