{
  "publishers": [], 
  "dimensions": "36 x 75 in. |  91.4 x 190.5 cm.", 
  "rights": null, 
  "credit_line": "Colonel Jeff W. Boucher Collection", 
  "artisinal:provider": "http://www.brooklynintegers.com/", 
  "title": "rug", 
  "accession_number": "1996.35", 
  "period": null, 
  "artisinal:id": 18154551, 
  "creation_date": "about 1870", 
  "dynasty": null, 
  "materials": "wool", 
  "actors": [], 
  "irn": 9790, 
  "printers": [], 
  "cultures": [
    "Baluchi people"
  ], 
  "on_view": false
}