{
  "publishers": [], 
  "dimensions": "H: 5/8 in. |  Diam: 2 7/8 in.", 
  "rights": null, 
  "credit_line": "Gift of Mr. and Mrs. John Mead in memory of Franklin B. Mead", 
  "artisinal:provider": "http://www.brooklynintegers.com/", 
  "title": "shallow dish", 
  "accession_number": "81.468", 
  "period": "Yongzheng", 
  "artisinal:id": 18153081, 
  "creation_date": "1723-1735", 
  "dynasty": "Qing dynasty", 
  "materials": "porcelain with overglaze enamel", 
  "actors": [], 
  "irn": 9170, 
  "printers": [], 
  "cultures": [], 
  "on_view": true
}