{
  "publishers": [], 
  "dimensions": null, 
  "rights": null, 
  "credit_line": "Gift of Hebbe Richardson and Elizabeth Bispham Knapp in memory of their parents", 
  "artisinal:provider": "http://www.brooklynintegers.com/", 
  "title": "tumbler (one of four)", 
  "accession_number": "81.115", 
  "period": null, 
  "artisinal:id": 18153187, 
  "creation_date": "about 1890-1937", 
  "dynasty": null, 
  "materials": "Colorless Soda-lime Glass | pressed", 
  "actors": [], 
  "irn": 9214, 
  "printers": [], 
  "cultures": [], 
  "on_view": false
}