{
  "publishers": [], 
  "dimensions": "20 x 34 in.(gong) L: 15 in. (beater", 
  "rights": null, 
  "credit_line": "Roger G. Wolcott Fund", 
  "artisinal:provider": "http://www.brooklynintegers.com/", 
  "title": "slit gong and beater", 
  "accession_number": "1988.31A-B", 
  "period": null, 
  "artisinal:id": 18154987, 
  "creation_date": null, 
  "dynasty": null, 
  "materials": "leather", 
  "actors": [], 
  "irn": 9971, 
  "printers": [], 
  "cultures": [
    "Songye people"
  ], 
  "on_view": false
}