{
  "publishers": [], 
  "artisinal:provider": "http://www.brooklynintegers.com/", 
  "dimensions": "L: 5 3/4 in.", 
  "credit_line": "Gift of Mr. and Mrs. William H. Ball", 
  "title": "spoon", 
  "rights": null, 
  "accession_number": "75.354.1", 
  "period": null, 
  "artisinal:id": 18201437, 
  "creation_date": null, 
  "materials": "hard paste porcelain, gilded, enamel over glaze", 
  "actors": [], 
  "irn": 23727, 
  "printers": [], 
  "cultures": [], 
  "dynasty": null, 
  "on_view": false
}