{
  "publishers": [], 
  "artisinal:provider": "http://www.brooklynintegers.com/", 
  "dimensions": "11 7/8 x 8 3/4 in.", 
  "credit_line": "The Eliza M. and Sarah L. Niblack Collection", 
  "title": "Saint John the Baptist", 
  "rights": null, 
  "accession_number": "33.1108", 
  "period": null, 
  "artisinal:id": 18202063, 
  "creation_date": "18th century", 
  "materials": "Silk Thread Glued On Parchment", 
  "actors": [], 
  "irn": 23997, 
  "printers": [], 
  "cultures": [], 
  "dynasty": null, 
  "on_view": false
}